detllm/__init__.py
detllm/api.py
detllm/logging.py
detllm/version.py
detllm/backends/__init__.py
detllm/backends/base.py
detllm/backends/hf.py
detllm/backends/vllm.py
detllm/cli/__init__.py
detllm/cli/main.py
detllm/core/__init__.py
detllm/core/artifacts.py
detllm/core/capabilities.py
detllm/core/deterministic.py
detllm/core/env.py
detllm/core/models.py
detllm/diff/__init__.py
detllm/diff/diff.py
detllm/report/__init__.py
detllm/report/render_text.py
detllm/report/report.py
detllm/schemas/__init__.py
detllm/trace/__init__.py
detllm/trace/io.py
detllm-0.1.1.dist-info/licenses/LICENSE
detllm-0.1.1.dist-info/METADATA
detllm-0.1.1.dist-info/WHEEL
detllm-0.1.1.dist-info/entry_points.txt
detllm-0.1.1.dist-info/top_level.txt
detllm-0.1.1.dist-info/RECORD
