Metadata-Version: 2.4
Name: detllm
Version: 0.1.1
Summary: Deterministic-mode checks for LLM inference: measure run/batch variance, generate repro packs, and explain why outputs differ.
Author: detLLM Contributors
License: Apache-2.0
Keywords: llm,determinism,reproducibility,inference
Classifier: Development Status :: 3 - Alpha
Classifier: License :: OSI Approved :: Apache Software License
Classifier: Programming Language :: Python :: 3
Classifier: Programming Language :: Python :: 3.10
Classifier: Programming Language :: Python :: 3.11
Classifier: Programming Language :: Python :: 3.12
Requires-Python: >=3.10
License-File: LICENSE
Provides-Extra: test
Requires-Dist: pytest>=7.0; extra == "test"
Provides-Extra: hf
Requires-Dist: torch; extra == "hf"
Requires-Dist: transformers; extra == "hf"
Provides-Extra: vllm
Requires-Dist: vllm; extra == "vllm"
Provides-Extra: schema
Requires-Dist: jsonschema; extra == "schema"
Provides-Extra: dev
Requires-Dist: pre-commit>=3.0; extra == "dev"
Requires-Dist: ruff>=0.5.0; extra == "dev"
Dynamic: license-file
